aiowire/__init__.py
aiowire/event_loop.py
aiowire/poller.py
aiowire/py.typed
aiowire/wire.py
aiowire-3.1.0.dist-info/COPYING
aiowire-3.1.0.dist-info/METADATA
aiowire-3.1.0.dist-info/WHEEL
aiowire-3.1.0.dist-info/RECORD
