Metadata-Version: 2.1
Name: aiowire
Version: 3.1.0
Summary: A simple event loop using asyncio
Home-page: https://github.com/frobnitzem/aiowire
License: LGPL-3.0-or-later
Author: David M. Rogers
Author-email: predictivestatmech@gmail.com
Requires-Python: >=3.8
Classifier: Development Status :: 4 - Beta
Classifier: Framework :: AsyncIO
Classifier: License :: OSI Approved :: GNU Lesser General Public License v3 or later (LGPLv3+)
Classifier: Programming Language :: Python :: 3
Classifier: Programming Language :: Python :: 3.8
Classifier: Programming Language :: Python :: 3.9
Classifier: Programming Language :: Python :: 3.10
Classifier: Programming Language :: Python :: 3.11
Classifier: Programming Language :: Python :: 3.12
Provides-Extra: zmq
Requires-Dist: pyzmq (>=23.2.0) ; extra == "zmq"
Project-URL: Repository, https://github.com/frobnitzem/aiowire
